waypoint_weaver/__init__.py
waypoint_weaver/cli.py
waypoint_weaver/config.py
waypoint_weaver/random_coordinates.py
waypoint_weaver/storage.py
waypoint_weaver/typing.py
waypoint_weaver/_data/example_config.yaml
waypoint_weaver-0.2.1.dist-info/METADATA
waypoint_weaver-0.2.1.dist-info/WHEEL
waypoint_weaver-0.2.1.dist-info/entry_points.txt
waypoint_weaver-0.2.1.dist-info/licenses/LICENSE
waypoint_weaver-0.2.1.dist-info/RECORD
