Metadata-Version: 2.4
Name: waypoint_weaver
Version: 0.2.1
Summary: A tool to generate a table of waypoints for a treasure hunt.
Project-URL: Documentation, https://github.com/unknown/project_name#readme
Project-URL: Issues, https://github.com/unknown/project_name/issues
Project-URL: Source, https://github.com/unknown/project_name
Author-email: Tim Adler <tim+github@emrys-merlin.de>
License-Expression: MIT
License-File: LICENSE
Classifier: Development Status :: 3 - Alpha
Classifier: License :: OSI Approved :: MIT License
Classifier: Programming Language :: Python :: 3
Classifier: Programming Language :: Python :: 3.12
Requires-Python: >=3.12
Requires-Dist: openpyxl>=3.1.5
Requires-Dist: pandas
Requires-Dist: pydantic>=2.0
Requires-Dist: pyyaml
Requires-Dist: tabulate
Requires-Dist: typer
